invisibleroads/__init__.py
invisibleroads/__main__.py
invisibleroads/scripts.py
invisibleroads-0.3.4.dist-info/METADATA
invisibleroads-0.3.4.dist-info/WHEEL
invisibleroads-0.3.4.dist-info/entry_points.txt
invisibleroads-0.3.4.dist-info/top_level.txt
invisibleroads-0.3.4.dist-info/zip-safe
invisibleroads-0.3.4.dist-info/RECORD
