Metadata-Version: 2.1
Name: invisibleroads
Version: 0.3.4
Summary: Simple framework for extensible command line scripts
Home-page: https://github.com/invisibleroads/invisibleroads
Author: Roy Hyunjin Han
Author-email: rhh@crosscompute.com
License: UNKNOWN
Keywords: invisibleroads
Platform: UNKNOWN
Classifier: Programming Language :: Python
Classifier: License :: OSI Approved :: MIT License
Requires-Dist: stevedore
